qcktypes/__init__.py
qcktypes/types.py
qcktypes-1.2.dist-info/LICENSE
qcktypes-1.2.dist-info/METADATA
qcktypes-1.2.dist-info/WHEEL
qcktypes-1.2.dist-info/top_level.txt
qcktypes-1.2.dist-info/RECORD
