Metadata-Version: 2.1
Name: qcktypes
Version: 1.2
Summary: Python implementation of dyne's file extension list
Home-page: https://github.com/smugvee/qcktypes
Author: smugvee
License: MIT
Classifier: Programming Language :: Python :: 3 :: Only
Classifier: License :: OSI Approved :: MIT License
Requires-Python: >=3.3
License-File: LICENSE
